holocron_ai/__init__.py
holocron_ai/__main__.py
holocron_ai/core/__init__.py
holocron_ai/core/beyond_dialog.py
holocron_ai/core/character_agent.py
holocron_ai/core/dialog_processor.py
holocron_ai/core/ditto_framework.py
holocron_ai/core/self_alignment.py
holocron_ai-0.1.1.dist-info/METADATA
holocron_ai-0.1.1.dist-info/WHEEL
holocron_ai-0.1.1.dist-info/entry_points.txt
holocron_ai-0.1.1.dist-info/top_level.txt
holocron_ai-0.1.1.dist-info/RECORD
