Metadata-Version: 2.4
Name: holocron-ai
Version: 0.1.1
Summary: A Star Wars character AI chat interface using PyQt and LLMs
Home-page: https://github.com/OldRepublicDevs/PyKotor
Author: PyKotor Team
Author-email: 
Maintainer-email: th3w1zard1 <halomastar@gmail.com>
License: MIT
Project-URL: Homepage, https://github.com/OldRepublicDevs/PyKotor
Project-URL: Documentation, https://github.com/OldRepublicDevs/PyKotor/wiki
Project-URL: Repository, https://github.com/OldRepublicDevs/PyKotor.git
Project-URL: Issues, https://github.com/OldRepublicDevs/PyKotor/issues
Keywords: kotor,star-wars,ai,llm,chat,character,roleplay,pyqt5,pykotor
Classifier: Development Status :: 3 - Alpha
Classifier: Intended Audience :: End Users/Desktop
Classifier: License :: OSI Approved :: MIT License
Classifier: Operating System :: OS Independent
Classifier: Programming Language :: Python :: 3
Classifier: Programming Language :: Python :: 3.8
Classifier: Programming Language :: Python :: 3.9
Classifier: Programming Language :: Python :: 3.10
Classifier: Programming Language :: Python :: 3.11
Classifier: Programming Language :: Python :: 3.12
Classifier: Topic :: Games/Entertainment
Classifier: Topic :: Scientific/Engineering :: Artificial Intelligence
Classifier: Environment :: X11 Applications :: Qt
Requires-Python: >=3.8
Requires-Dist: pykotor>=2.0.2
Provides-Extra: dev
Requires-Dist: pytest>=7.0.0; extra == "dev"
Requires-Dist: ruff>=0.1.0; extra == "dev"
Dynamic: home-page
Dynamic: requires-python
